README.md
setup.cfg
setup.py
gameroom_kit/__init__.py
gameroom_kit.egg-info/PKG-INFO
gameroom_kit.egg-info/SOURCES.txt
gameroom_kit.egg-info/dependency_links.txt
gameroom_kit.egg-info/top_level.txt
gameroom_kit/helpers/__init__.py
gameroom_kit/helpers/clearLine.py
gameroom_kit/helpers/getAll.py
gameroom_kit/lib/Comparison.py
gameroom_kit/lib/Expression.py
gameroom_kit/lib/Filter.py
gameroom_kit/lib/__init__.py
gameroom_kit/models/Address.py
gameroom_kit/models/Adjustment.py
gameroom_kit/models/Base.py
gameroom_kit/models/Charge.py
gameroom_kit/models/Container.py
gameroom_kit/models/Customer.py
gameroom_kit/models/Gift_Certificate.py
gameroom_kit/models/Image.py
gameroom_kit/models/Line.py
gameroom_kit/models/Note.py
gameroom_kit/models/Option.py
gameroom_kit/models/Option_Group.py
gameroom_kit/models/Payment.py
gameroom_kit/models/Price.py
gameroom_kit/models/Price_Option_Group.py
gameroom_kit/models/Product.py
gameroom_kit/models/Sale.py
gameroom_kit/models/Slide.py
gameroom_kit/models/Slideshow.py
gameroom_kit/models/Store.py
gameroom_kit/models/Tag.py
gameroom_kit/models/Tax.py
gameroom_kit/models/Till.py
gameroom_kit/models/Timecard.py
gameroom_kit/models/Token.py
gameroom_kit/models/Unit.py
gameroom_kit/models/Unit_Option.py
gameroom_kit/models/Unit_Tag.py
gameroom_kit/models/User.py
gameroom_kit/models/__init__.py