Metadata-Version: 2.1
Name: gameroom-kit
Version: 0.0.7
Summary: A Python package for the Gameroom API
Home-page: https://github.com/gameroomforpresident/GameroomKit-Python
Author: InfiniteToken
Author-email: infinitetoken@gmail.com
License: UNKNOWN
Platform: UNKNOWN
Classifier: Programming Language :: Python :: 3
Classifier: License :: OSI Approved :: MIT License
Classifier: Operating System :: OS Independent
